nebula_loader-0.1.1.dist-info/METADATA
nebula_loader-0.1.1.dist-info/WHEEL
nebula_loader/__init__.py
nebula_loader/ng_load.py
nebula_loader-0.1.1.dist-info/RECORD
