Metadata-Version: 2.1
Name: nebula_loader
Version: 0.1.1
Summary: Load from awesome-dataset into NebulaGraph
Requires-Python: >=3.8
Requires-Dist: requests>=2.31.0
Requires-Dist: pandas>=2.0.3
Requires-Dist: pydantic>=2.7.1
Requires-Dist: tqdm>=4.66.2
Requires-Dist: nebula3-python>=3.8
